nlpsych/__init__.py
nlpsych/descriptive_stats.py
nlpsych/embedding.py
nlpsych/modeling.py
nlpsych/report.py
nlpsych/utils.py
nlpsych-0.1.3.dist-info/licenses/LICENSE
nlpsych_app/__init__.py
nlpsych_app/app.py
nlpsych_app/launch.py
nlpsych_app/.streamlit/config.toml
nlpsych_app/assets/NLPsych_logo.png
nlpsych-0.1.3.dist-info/METADATA
nlpsych-0.1.3.dist-info/WHEEL
nlpsych-0.1.3.dist-info/entry_points.txt
nlpsych-0.1.3.dist-info/top_level.txt
nlpsych-0.1.3.dist-info/RECORD
