Metadata-Version: 2.4
Name: NLPsych
Version: 0.1.3
Summary: Tools for text analysis, embeddings, and lightweight modeling with a Streamlit app interface.
Author-email: Shawn Manuel <shawn.stephen.manuel@gmail.com>
License: MIT
Project-URL: Homepage, https://github.com/shwnmnl/NLPsych
Project-URL: Issues, https://github.com/shwnmnl/NLPsych/issues
Classifier: Programming Language :: Python :: 3
Classifier: Programming Language :: Python :: 3 :: Only
Classifier: License :: OSI Approved :: MIT License
Classifier: Operating System :: OS Independent
Classifier: Intended Audience :: Science/Research
Classifier: Topic :: Scientific/Engineering :: Information Analysis
Requires-Python: >=3.9
License-File: LICENSE
Requires-Dist: pandas>=2.2
Requires-Dist: numpy<2.0,>=1.26
Requires-Dist: spacy<3.9,>=3.8
Requires-Dist: scikit-learn>=1.5
Requires-Dist: statsmodels>=0.14
Requires-Dist: sentence-transformers>=3.0
Requires-Dist: umap-learn>=0.5
Requires-Dist: plotly>=5.22
Requires-Dist: tabulate>=0.9.0
Provides-Extra: app
Requires-Dist: streamlit>=1.39; extra == "app"
Provides-Extra: dev
Requires-Dist: pytest>=8; extra == "dev"
Requires-Dist: ruff>=0.5; extra == "dev"
Requires-Dist: black>=24; extra == "dev"
Dynamic: license-file
